nonebot_plugin_pictranslator/__init__.py
nonebot_plugin_pictranslator/config.py
nonebot_plugin_pictranslator/define.py
nonebot_plugin_pictranslator/translate.py
nonebot_plugin_pictranslator/utils.py
nonebot_plugin_pictranslator/apis/__init__.py
nonebot_plugin_pictranslator/apis/baidu.py
nonebot_plugin_pictranslator/apis/baidu_cloud.py
nonebot_plugin_pictranslator/apis/base_api.py
nonebot_plugin_pictranslator/apis/tencent.py
nonebot_plugin_pictranslator/apis/tianapi.py
nonebot_plugin_pictranslator/apis/utils.py
nonebot_plugin_pictranslator/apis/youdao.py
nonebot_plugin_pictranslator/apis/response_models/__init__.py
nonebot_plugin_pictranslator/apis/response_models/baidu.py
nonebot_plugin_pictranslator/apis/response_models/baidu_cloud.py
nonebot_plugin_pictranslator/apis/response_models/base_response_model.py
nonebot_plugin_pictranslator/apis/response_models/tencent.py
nonebot_plugin_pictranslator/apis/response_models/tianapi.py
nonebot_plugin_pictranslator/apis/response_models/youdao.py
nonebot_plugin_pictranslator-1.0.10.dist-info/licenses/LICENSE
nonebot_plugin_pictranslator-1.0.10.dist-info/METADATA
nonebot_plugin_pictranslator-1.0.10.dist-info/WHEEL
nonebot_plugin_pictranslator-1.0.10.dist-info/top_level.txt
nonebot_plugin_pictranslator-1.0.10.dist-info/RECORD
