Metadata-Version: 2.4
Name: nonebot-plugin-pictranslator
Version: 1.0.10
Summary: 一个支持图片翻译的nonebot2插件
Author: iona-s
License: MIT
Project-URL: homepage, https://github.com/iona-s/nonebot-plugin-pictranslator
Project-URL: repository, https://github.com/iona-s/nonebot-plugin-pictranslator
Requires-Python: <4.0,>=3.9
License-File: LICENSE
Requires-Dist: httpx>=0.27.0
Requires-Dist: langcodes>=3.5.0
Requires-Dist: nonebot-plugin-alconna>=0.54.0
Requires-Dist: nonebot2>=2.4.0
Requires-Dist: pillow>=10.0.0
Dynamic: license-file
